async_irc_client/__init__.py
async_irc_client/async_irc_client.py
AsyncIRCClient-1.0.3.dist-info/LICENSE
AsyncIRCClient-1.0.3.dist-info/METADATA
AsyncIRCClient-1.0.3.dist-info/WHEEL
AsyncIRCClient-1.0.3.dist-info/top_level.txt
AsyncIRCClient-1.0.3.dist-info/RECORD
