Metadata-Version: 2.2
Name: AsyncIRCClient
Version: 1.0.3
Summary: Async IRC Client
Author: CoreTaxxe
Author-email: coretaxxe@gmail.com
License-File: LICENSE
Requires-Dist: loguru
Requires-Dist: python_socks
Dynamic: author
Dynamic: author-email
Dynamic: description
Dynamic: description-content-type
Dynamic: requires-dist
Dynamic: summary
